multifit/UI.py
multifit/__init__.py
multifit/fitting.py
tests/__init__.py
multifit-1.0.1.0.dist-info/LICENCE
multifit-1.0.1.0.dist-info/METADATA
multifit-1.0.1.0.dist-info/WHEEL
multifit-1.0.1.0.dist-info/top_level.txt
multifit-1.0.1.0.dist-info/RECORD
