Metadata-Version: 2.1
Name: multifit
Version: 1.0.1.0
Summary: Tool for fitting multiple data sets with shared parameters simultaneously
Home-page: https://github.com/johashei/multifit
Author: Johannes Sørby Heines
Author-email: j.s.heines@fys.uio.no
License: UNKNOWN
Platform: UNKNOWN
Classifier: Development Status :: 5 - Production/Stable
Classifier: Intended Audience :: Science/Research
Classifier: Topic :: Scientific/Engineering :: Physics
Classifier: License :: OSI Approved :: MIT License
Classifier: Operating System :: MacOS
Classifier: Programming Language :: Python :: 3.9
License-File: LICENCE
Requires-Dist: numpy
Requires-Dist: scipy
Requires-Dist: matplotlib
Requires-Dist: iminuit
Requires-Dist: pathlib
